gaphas/__init__.py
gaphas/canvas.py
gaphas/connections.py
gaphas/connector.py
gaphas/constraint.py
gaphas/cursor.py
gaphas/geometry.py
gaphas/guide.py
gaphas/handle.py
gaphas/handlemove.py
gaphas/item.py
gaphas/matrix.py
gaphas/model.py
gaphas/move.py
gaphas/painter/__init__.py
gaphas/painter/chain.py
gaphas/painter/freehand.py
gaphas/painter/handlepainter.py
gaphas/painter/itempainter.py
gaphas/painter/painter.py
gaphas/port.py
gaphas/position.py
gaphas/quadtree.py
gaphas/segment.py
gaphas/selection.py
gaphas/solver/__init__.py
gaphas/solver/constraint.py
gaphas/solver/solver.py
gaphas/solver/variable.py
gaphas/table.py
gaphas/tool/__init__.py
gaphas/tool/hover.py
gaphas/tool/itemtool.py
gaphas/tool/placement.py
gaphas/tool/rubberband.py
gaphas/tool/scroll.py
gaphas/tool/viewfocus.py
gaphas/tool/zoom.py
gaphas/tree.py
gaphas/types.py
gaphas/view/__init__.py
gaphas/view/gtkview.py
gaphas/view/scrolling.py
gaphas-5.1.2.dist-info/LICENSES/Apache-2.0.txt
gaphas-5.1.2.dist-info/METADATA
gaphas-5.1.2.dist-info/WHEEL
gaphas-5.1.2.dist-info/RECORD
