Metadata-Version: 2.3
Name: gaphas
Version: 5.1.2
Summary: Gaphas is a GTK diagramming widget
Keywords: gtk,diagram,gaphas
Author: Arjan Molenaar
Author-email: gaphor@gmail.com
Requires-Python: >=3.9,<4.0
Classifier: Development Status :: 5 - Production/Stable
Classifier: Environment :: X11 Applications :: GTK
Classifier: Intended Audience :: Developers
Classifier: License :: OSI Approved :: Apache Software License
Classifier: Programming Language :: Python
Classifier: Topic :: Software Development :: Libraries :: Python Modules
Requires-Dist: PyGObject (>=3.50)
Requires-Dist: pycairo (>=1.20.0)
Project-URL: Documentation, https://gaphas.readthedocs.io/
Project-URL: Homepage, https://gaphas.readthedocs.io/
Project-URL: Repository, https://github.com/gaphor/gaphas
